st_clipboard/__init__.py
st_clipboard-0.0.1.dist-info/LICENSE
st_clipboard-0.0.1.dist-info/METADATA
st_clipboard-0.0.1.dist-info/WHEEL
st_clipboard-0.0.1.dist-info/top_level.txt
st_clipboard-0.0.1.dist-info/RECORD
