Metadata-Version: 2.1
Name: st-clipboard
Version: 0.0.1
Summary: A lightweight clipboard copy utility for Streamlit, supporting both HTTP and HTTPS environments seamlessly.
Home-page: https://github.com/Haloroute/st-clipboard
Author: Haloroute
Author-email: quangtuyensctn@gmail.com
Classifier: Programming Language :: Python :: 3
Classifier: License :: OSI Approved :: MIT License
Classifier: Operating System :: OS Independent
License-File: LICENSE
